tomato_bronkhorst/__init__.py
tomato_bronkhorst-2.1.0.dist-info/licenses/LICENSE
tomato_bronkhorst-2.1.0.dist-info/METADATA
tomato_bronkhorst-2.1.0.dist-info/WHEEL
tomato_bronkhorst-2.1.0.dist-info/top_level.txt
tomato_bronkhorst-2.1.0.dist-info/RECORD
